emails_mcp/__init__.py
emails_mcp/__main__.py
emails_mcp/server.py
emails_mcp/backends/__init__.py
emails_mcp/backends/file_backend.py
emails_mcp/backends/imap_backend.py
emails_mcp/backends/smtp_backend.py
emails_mcp/config/__init__.py
emails_mcp/config/settings.py
emails_mcp/models/__init__.py
emails_mcp/models/config.py
emails_mcp/models/email.py
emails_mcp/services/__init__.py
emails_mcp/services/draft_service.py
emails_mcp/services/email_service.py
emails_mcp/services/folder_service.py
emails_mcp/services/search_service.py
emails_mcp/tools/__init__.py
emails_mcp/tools/email_tools.py
emails_mcp/tools/folder_tools.py
emails_mcp/tools/management_tools.py
emails_mcp/utils/__init__.py
emails_mcp/utils/email_parser.py
emails_mcp/utils/encode_decode.py
emails_mcp/utils/exceptions.py
emails_mcp/utils/validators.py
emails_mcp-0.1.12.dist-info/METADATA
emails_mcp-0.1.12.dist-info/WHEEL
emails_mcp-0.1.12.dist-info/entry_points.txt
emails_mcp-0.1.12.dist-info/licenses/LICENSE
emails_mcp-0.1.12.dist-info/RECORD
