Metadata-Version: 2.4
Name: emails-mcp
Version: 0.1.12
Summary: A FastMCP-based email management server for IMAP/SMTP operations
Author-email: lockon-n <lockonlvange@gmail.com>
License-File: LICENSE
Requires-Python: >=3.12
Requires-Dist: beautifulsoup4>=4.13.4
Requires-Dist: email-validator>=2.1.1
Requires-Dist: fastmcp>=2.10.5
Requires-Dist: imapclient>=3.0.1
Requires-Dist: mcp[cli]>=1.11.0
Requires-Dist: requests>=2.32.4
Requires-Dist: typing-extensions>=4.9.0
